setup.py
pds_nds_p/Binomialdistribution.py
pds_nds_p/Gaussiandistribution.py
pds_nds_p/Generaldistribution.py
pds_nds_p/__init__.py
pds_nds_p/test.py
pds_nds_p.egg-info/PKG-INFO
pds_nds_p.egg-info/SOURCES.txt
pds_nds_p.egg-info/dependency_links.txt
pds_nds_p.egg-info/not-zip-safe
pds_nds_p.egg-info/top_level.txt