Metadata-Version: 2.1
Name: pds-nds-p
Version: 0.1
Summary: Gaussian distributions
Home-page: UNKNOWN
Author: Mohamed Javeed
Author-email: javeedrstar5@gmail.com
License: UNKNOWN
Platform: UNKNOWN
